[
  {
    "close": 15832.8,
    "date": "2022-01-03T07:00:00.000Z",
    "jst": "2022/01/04 06:00:00",
    "utc": "2022/01/03 21:00:00",
    "week": 2
  },
  {
    "close": 15622.72,
    "date": "2022-01-04T07:00:00.000Z",
    "jst": "2022/01/05 06:00:00",
    "utc": "2022/01/04 21:00:00",
    "week": 2
  },
  {
    "close": 15100.17,
    "date": "2022-01-05T07:00:00.000Z",
    "jst": "2022/01/06 06:00:00",
    "utc": "2022/01/05 21:00:00",
    "week": 2
  },
  {
    "close": 15080.87,
    "date": "2022-01-06T07:00:00.000Z",
    "jst": "2022/01/07 06:00:00",
    "utc": "2022/01/06 21:00:00",
    "week": 2
  },
  {
    "change": -896.8999999999996,
    "changepct": -6,
    "close": 14935.9,
    "date": "2022-01-07T07:00:00.000Z",
    "jst": "2022/01/08 06:00:00",
    "utc": "2022/01/07 21:00:00",
    "week": 2
  },
  {
    "close": 14942.83,
    "date": "2022-01-10T07:00:00.000Z",
    "jst": "2022/01/11 06:00:00",
    "utc": "2022/01/10 21:00:00",
    "week": 3
  },
  {
    "close": 15153.45,
    "date": "2022-01-11T07:00:00.000Z",
    "jst": "2022/01/12 06:00:00",
    "utc": "2022/01/11 21:00:00",
    "week": 3
  },
  {
    "close": 15188.39,
    "date": "2022-01-12T07:00:00.000Z",
    "jst": "2022/01/13 06:00:00",
    "utc": "2022/01/12 21:00:00",
    "week": 3
  },
  {
    "close": 14806.81,
    "date": "2022-01-13T07:00:00.000Z",
    "jst": "2022/01/14 06:00:00",
    "utc": "2022/01/13 21:00:00",
    "week": 3
  },
  {
    "change": -49.07999999999993,
    "changepct": -0.33,
    "close": 14893.75,
    "date": "2022-01-14T07:00:00.000Z",
    "jst": "2022/01/15 06:00:00",
    "utc": "2022/01/14 21:00:00",
    "week": 3
  },
  {
    "close": 14506.9,
    "date": "2022-01-18T07:00:00.000Z",
    "jst": "2022/01/19 06:00:00",
    "utc": "2022/01/18 21:00:00",
    "week": 4
  },
  {
    "close": 14340.26,
    "date": "2022-01-19T07:00:00.000Z",
    "jst": "2022/01/20 06:00:00",
    "utc": "2022/01/19 21:00:00",
    "week": 4
  },
  {
    "close": 14154.02,
    "date": "2022-01-20T07:00:00.000Z",
    "jst": "2022/01/21 06:00:00",
    "utc": "2022/01/20 21:00:00",
    "week": 4
  },
  {
    "change": -737.9799999999996,
    "changepct": -5.36,
    "close": 13768.92,
    "date": "2022-01-21T07:00:00.000Z",
    "jst": "2022/01/22 06:00:00",
    "utc": "2022/01/21 21:00:00",
    "week": 4
  },
  {
    "close": 13855.13,
    "date": "2022-01-24T07:00:00.000Z",
    "jst": "2022/01/25 06:00:00",
    "utc": "2022/01/24 21:00:00",
    "week": 5
  },
  {
    "change": -315.8299999999999,
    "changepct": -2.33,
    "close": 13539.3,
    "date": "2022-01-25T07:00:00.000Z",
    "jst": "2022/01/26 06:00:00",
    "utc": "2022/01/25 21:00:00",
    "week": 5
  }
]